cxfiler/__init__.py
cxfiler/base.py
cxfiler/main.py
cxfiler/multiline_strings.py
cxfiler/screens/__init__.py
cxfiler/screens/actions.py
cxfiler/screens/filelist.py
cxfiler/screens/help.py
cxfiler/screens/rename.py
cxfiler/strings.py
cxfiler/utils.py
cxfiler-1.0.1.dist-info/LICENSE
cxfiler-1.0.1.dist-info/METADATA
cxfiler-1.0.1.dist-info/WHEEL
cxfiler-1.0.1.dist-info/entry_points.txt
cxfiler-1.0.1.dist-info/RECORD
