Metadata-Version: 2.1
Name: cxfiler
Version: 1.0.1
Summary: An intuitive, modern file explorer for use in a terminal
License: BSD-2-Clause
Author: Charlie Koch
Author-email: charles@cerrax.com
Requires-Python: >=3.9,<4.0
Classifier: License :: OSI Approved :: BSD License
Classifier: Programming Language :: Python :: 3
Classifier: Programming Language :: Python :: 3.9
Classifier: Programming Language :: Python :: 3.10
Classifier: Programming Language :: Python :: 3.11
Classifier: Programming Language :: Python :: 3.12
Classifier: Programming Language :: Python :: 3.13
Requires-Dist: bwk (==1.1.0)
Requires-Dist: cerrax-py (==1.0.0)
Project-URL: Changelog, https://gitlab.com/charles.w.koch/filer/-/blob/main/CHANGELOG.md
Project-URL: Homepage, http://cerrax.com
Project-URL: Repository, https://gitlab.com/charles.w.koch/filer
